AUTHORS
ChangeLog
LICENSE
README.md
setup.cfg
setup.py
pylinx/__init__.py
pylinx/core.py
pylinx.egg-info/PKG-INFO
pylinx.egg-info/SOURCES.txt
pylinx.egg-info/dependency_links.txt
pylinx.egg-info/not-zip-safe
pylinx.egg-info/pbr.json
pylinx.egg-info/requires.txt
pylinx.egg-info/top_level.txt
tests/dummy_vivado.tcl
tests/dummy_xsct.tcl
tests/test_dummy_vivado.py
tests/test_dummy_xsct.py