Metadata-Version: 2.1
Name: pylinx
Version: 0.0.1.dev3
Summary: Python utils for Xilinx's tools
Home-page: UNKNOWN
Author: Benedek Racz
Author-email: betontalpfa@gmail.com
License: Apache License, Version 2.0
Project-URL: Source Code, https://github.com/raczben/pylinx
Keywords: FPGA, Xilinx, Vivado, SDK, XSDK, scripting, automation, expect, pexpect, wexpect
Platform: UNKNOWN
Classifier: Development Status :: 4 - Beta
Classifier: Environment :: Console
Classifier: Intended Audience :: Developers
Classifier: Intended Audience :: Information Technology
Classifier: Programming Language :: Python :: 3.3
Classifier: Programming Language :: Python :: 3.4
Classifier: Programming Language :: Python :: 3.5
Classifier: Programming Language :: Python :: 3.6
Classifier: Programming Language :: Python :: 3.7
Provides-Extra: test
